tovala_insights/__init__.py
tovala_insights/data_load.py
tovala_insights/log_config.py
tovala_insights/configuration/__init__.py
tovala_insights/configuration/log_config.yaml
tovala_insights-1.9.dist-info/METADATA
tovala_insights-1.9.dist-info/WHEEL
tovala_insights-1.9.dist-info/top_level.txt
tovala_insights-1.9.dist-info/RECORD
