Metadata-Version: 2.1
Name: tovala-insights
Version: 1.9
Summary: "Tovala Coding Assessment - A python CLI to extract data and generate insights"
Home-page: https://github.com/Aditya2810/Aditya2810.git
Author: Aditya
Author-email: adityal2810@gmail.com
License: UNKNOWN
Platform: UNKNOWN
Requires-Python: >=3.7
Requires-Dist: requests
Requires-Dist: pathlib
Requires-Dist: PyYaml
Requires-Dist: click
Requires-Dist: wheel
Requires-Dist: setuptools (>=40.2.0)
Requires-Dist: twine
